{"chunk_definitions":[{"row":14,"row_count":1,"visible":true,"expansion_state":0,"options":{"engine":"r","label":"setup","include":false},"document_id":"E253AAAA","chunk_id":"csetup_chunk","chunk_label":"setup"},{"row":20,"row_count":1,"visible":true,"expansion_state":0,"options":{"engine":"r","label":"unnamed-chunk-7"},"document_id":"E253AAAA","chunk_id":"ci1q06mlk4no5","chunk_label":"unnamed-chunk-1"},{"row":24,"row_count":1,"visible":true,"expansion_state":0,"options":{"engine":"r","label":"unnamed-chunk-8"},"document_id":"E253AAAA","chunk_id":"cyr5xkrrtbbd8","chunk_label":"unnamed-chunk-2"},{"row":28,"row_count":1,"visible":true,"expansion_state":0,"options":{"engine":"r","label":"unnamed-chunk-10"},"document_id":"E253AAAA","chunk_id":"csqu8dh4apa65","chunk_label":"unnamed-chunk-3"}],"doc_write_time":1593854836,"working_dir":null,"default_chunk_options":{}}